py_pushover_client/__init__.py
py_pushover_client-1.0.0.dev2.dist-info/METADATA
py_pushover_client-1.0.0.dev2.dist-info/WHEEL
py_pushover_client-1.0.0.dev2.dist-info/licenses/LICENSE
py_pushover_client-1.0.0.dev2.dist-info/RECORD
