Metadata-Version: 2.1
Name: py_pushover_client
Version: 1.0.0.dev2
Summary: A client package for the Pushover API
Project-URL: Homepage, https://github.com/simplytim42/py-pushover-client
Author-email: Tim MacKay <simplytim42@gmail.com>
License: MIT License
License-File: LICENSE
Classifier: License :: OSI Approved :: MIT License
Classifier: Programming Language :: Python :: 3
Requires-Python: >=3.7
Requires-Dist: requests>=2.31.0
